qosst_bob/__init__.py
qosst_bob/bob.py
qosst_bob/data.py
qosst_bob/dsp/__init__.py
qosst_bob/dsp/dsp.py
qosst_bob/dsp/equalizers.py
qosst_bob/dsp/pilots.py
qosst_bob/dsp/resample.py
qosst_bob/dsp/zc.py
qosst_bob/excess_noise.py
qosst_bob/gui/__init__.py
qosst_bob/gui/bobgui.py
qosst_bob/gui/figures.py
qosst_bob/gui/layout.py
qosst_bob/gui/layout_content.py
qosst_bob/gui/logo.png
qosst_bob/gui/plot_styles/old-style.mplstyle
qosst_bob/gui/plot_styles/paper.mplstyle
qosst_bob/gui/plot_utils.py
qosst_bob/optimization/__init__.py
qosst_bob/optimization/commands.py
qosst_bob/optimization/optimize.py
qosst_bob/optimization/updaters/__init__.py
qosst_bob/optimization/updaters/average_tone_size.py
qosst_bob/optimization/updaters/baud_rate.py
qosst_bob/optimization/updaters/conversion_factor.py
qosst_bob/optimization/updaters/frequency_cutoff_tone.py
qosst_bob/optimization/updaters/frequency_shift.py
qosst_bob/optimization/updaters/pilot_difference.py
qosst_bob/optimization/updaters/pilots_amplitude.py
qosst_bob/optimization/updaters/roll_off.py
qosst_bob/optimization/updaters/subframe_size.py
qosst_bob/optimization/updaters/xi_versus_va.py
qosst_bob/parameters_estimation/__init__.py
qosst_bob/parameters_estimation/base.py
qosst_bob/py.typed
qosst_bob/tools/__init__.py
qosst_bob/tools/calibrate_eta_current.py
qosst_bob/tools/calibrate_eta_voltage.py
qosst_bob/tools/commands.py
qosst_bob/transmittance.py
qosst_bob/utils.py
qosst_bob-0.10.2.dist-info/LICENSE
qosst_bob-0.10.2.dist-info/METADATA
qosst_bob-0.10.2.dist-info/WHEEL
qosst_bob-0.10.2.dist-info/entry_points.txt
qosst_bob-0.10.2.dist-info/RECORD
