Metadata-Version: 2.1
Name: qosst-bob
Version: 0.10.2
Summary: Bob submodule of QOSST, containing modules for Bob client, the GUI, the DSP of Bob and parameters estimation.
Home-page: https://github.com/qosst
License: GPLv3
Author: Yoann Piétri
Author-email: Yoann.Pietri@lip6.fr
Requires-Python: >=3.9,<3.13
Classifier: Development Status :: 4 - Beta
Classifier: Intended Audience :: Science/Research
Classifier: License :: OSI Approved :: GNU General Public License v3 (GPLv3)
Classifier: License :: Other/Proprietary License
Classifier: Natural Language :: English
Classifier: Operating System :: OS Independent
Classifier: Programming Language :: Python :: 3
Classifier: Programming Language :: Python :: 3.9
Classifier: Programming Language :: Python :: 3.10
Classifier: Programming Language :: Python :: 3.11
Classifier: Programming Language :: Python :: 3.12
Classifier: Topic :: Scientific/Engineering :: Physics
Classifier: Topic :: Security :: Cryptography
Requires-Dist: freesimplegui (>=5.1.0,<6.0.0)
Requires-Dist: matplotlib (>=3.5.1,<4.0.0) ; python_version >= "3.9" and python_version < "3.11"
Requires-Dist: matplotlib (>=3.7.1,<4.0.0) ; python_version >= "3.11" and python_version < "3.13"
Requires-Dist: qosst-core (>=0.10.0,<0.11.0)
Requires-Dist: qosst-hal (>=0.10.0,<0.11.0)
Requires-Dist: qosst-skr (>=0.10.0,<0.11.0)
Requires-Dist: scipy (>=1.10,<2.0)
Project-URL: Documentation, https://qosst-bob.readthedocs.io/
Project-URL: Repository, https://github.com/qosst/qosst-bob
